deploy/__init__.py
deploy/main.py
scripts/__init__.py
wpkit/__init__.py
wpkit/__main__.py
wpkit/data.py
wpkit/heart.py
wpkit/install.py
wpkit/pan.py
wpkit/piu.py
wpkit/pjtools.py
wpkit/pkg_info.py
wpkit/pygit.py
wpkit/run.py
wpkit/utils.py
wpkit/basic/__init__.py
wpkit/basic/basic.py
wpkit/basic/classes.py
wpkit/basic/filetools.py
wpkit/basic/functions.py
wpkit/cli/__init__.py
wpkit/cli/wk-fs.bat
wpkit/cli/wk-heart.bat
wpkit/cli/wk-heart.sh
wpkit/cli/wk-hi.bat
wpkit/cli/wk-hi.py
wpkit/cli/wk-hi.sh
wpkit/cli/wk-menu.bat
wpkit/cli/wk-run.bat
wpkit/cli/wk-update.bat
wpkit/cli/wk-update.sh
wpkit/cli/wk.bat
wpkit/cli/wk.py
wpkit/cv/__init__.py
wpkit/cv/all.py
wpkit/cv/cli.py
wpkit/cv/color.py
wpkit/cv/cv.py
wpkit/cv/annotation/__init__.py
wpkit/cv/annotation/yolo.py
wpkit/cv/augment/__init__.py
wpkit/cv/augment/cv2.py
wpkit/cv/augment/pil.py
wpkit/cv/datasets/__init__.py
wpkit/cv/datasets/cifar10.py
wpkit/cv/datasets/scripts/__init__.py
wpkit/cv/datasets/scripts/convert_cifar10.py
wpkit/cv/datasets/scripts/make_ssl_dataset.py
wpkit/cv/datasets/scripts/split_train_val.py
wpkit/cv/examples/__init__.py
wpkit/cv/examples/keras/__init__.py
wpkit/cv/examples/keras/MobilenetV2/__init__.py
wpkit/cv/examples/keras/MobilenetV2/test.py
wpkit/cv/examples/keras/MobilenetV2/train.py
wpkit/cv/examples/lpr/__init__.py
wpkit/cv/examples/lpr/test.py
wpkit/cv/examples/lpr/val.py
wpkit/cv/examples/resnet/__init__.py
wpkit/cv/examples/resnet/train.py
wpkit/cv/examples/torch/__init__.py
wpkit/cv/examples/torch/resnet/__init__.py
wpkit/cv/examples/torch/resnet/predict.py
wpkit/cv/examples/torch/resnet/test.py
wpkit/cv/examples/torch/resnet/train.py
wpkit/cv/examples/torch/resnet/val.py
wpkit/cv/examples/torch/resnet_dev/__init__.py
wpkit/cv/examples/torch/resnet_dev/test.py
wpkit/cv/examples/torch/resnet_dev/train.py
wpkit/cv/examples/torch/resnet_dev/val.py
wpkit/cv/examples/yolo/__init__.py
wpkit/cv/examples/yolo/convert_annotations.py
wpkit/cv/examples/yolo/model.py
wpkit-1.1.2.4.dist-info/LICENSE
wpkit-1.1.2.4.dist-info/METADATA
wpkit-1.1.2.4.dist-info/WHEEL
wpkit-1.1.2.4.dist-info/entry_points.txt
wpkit-1.1.2.4.dist-info/top_level.txt
wpkit-1.1.2.4.dist-info/RECORD
