Metadata-Version: 2.1
Name: wpkit
Version: 1.1.2.4
Summary: A small example package
Home-page: https://github.com/Peiiii/wpkit
Author: WangPei
Author-email: 1535376447@qq.com
License: UNKNOWN
Platform: UNKNOWN
Classifier: Programming Language :: Python :: 3
Classifier: License :: OSI Approved :: MIT License
Classifier: Operating System :: OS Independent
Requires-Python: >=3.0
